color_zone_processor/__init__.py
color_zone_processor/cli.py
color_zone_processor/processor.py
color_zone_processor-0.1.0.dist-info/licenses/LICENSE
color_zone_processor-0.1.0.dist-info/METADATA
color_zone_processor-0.1.0.dist-info/WHEEL
color_zone_processor-0.1.0.dist-info/entry_points.txt
color_zone_processor-0.1.0.dist-info/top_level.txt
color_zone_processor-0.1.0.dist-info/RECORD
