Metadata-Version: 2.4
Name: color_zone_processor
Version: 0.1.0
Summary: A tool for processing image color zones
Home-page: https://github.com/yourusername/color_zone_processor
Author: Your Name
Author-email: your.email@example.com
Classifier: Programming Language :: Python :: 3
Classifier: License :: OSI Approved :: MIT License
Classifier: Operating System :: OS Independent
Requires-Python: >=3.6
License-File: LICENSE
Requires-Dist: Pillow>=10.2.0
Requires-Dist: numpy>=1.26.4
Requires-Dist: scipy>=1.12.0
Dynamic: author
Dynamic: author-email
Dynamic: classifier
Dynamic: description
Dynamic: description-content-type
Dynamic: home-page
Dynamic: license-file
Dynamic: requires-dist
Dynamic: requires-python
Dynamic: summary
